interpolatepy/__init__.py
interpolatepy/b_spline.py
interpolatepy/b_spline_approx.py
interpolatepy/b_spline_cubic.py
interpolatepy/b_spline_interpolate.py
interpolatepy/b_spline_smooth.py
interpolatepy/c_s_smoot_search.py
interpolatepy/c_s_smoothing.py
interpolatepy/c_s_with_acc1.py
interpolatepy/c_s_with_acc2.py
interpolatepy/cubic_spline.py
interpolatepy/double_s.py
interpolatepy/frenet_frame.py
interpolatepy/lin_poly_parabolic.py
interpolatepy/linear.py
interpolatepy/log_quat.py
interpolatepy/polynomials.py
interpolatepy/quat_core.py
interpolatepy/quat_spline.py
interpolatepy/quat_visualization.py
interpolatepy/simple_paths.py
interpolatepy/squad_c2.py
interpolatepy/trapezoidal.py
interpolatepy/tridiagonal_inv.py
interpolatepy/version.py
interpolatepy-2.0.1.dist-info/licenses/LICENSE
interpolatepy-2.0.1.dist-info/METADATA
interpolatepy-2.0.1.dist-info/WHEEL
interpolatepy-2.0.1.dist-info/top_level.txt
interpolatepy-2.0.1.dist-info/RECORD
