Metadata-Version: 2.4
Name: InterpolatePy
Version: 2.0.1
Summary: A comprehensive Python library for generating smooth trajectories and curves with precise control over position, velocity, acceleration, and jerk profiles
Author-email: Giorgio Medico <giorgio.medico11@gmail.com>
Maintainer-email: Giorgio Medico <giorgio.medico11@gmail.com>
License-Expression: MIT
Project-URL: Homepage, https://github.com/GiorgioMedico/InterpolatePy
Project-URL: Bug Tracker, https://github.com/GiorgioMedico/InterpolatePy/issues
Keywords: interpolation,trajectory planning,motion profiles,robotics,b-splines,cubic splines,frenet frames,path generation,motion control
Platform: unix
Platform: linux
Platform: osx
Platform: cygwin
Platform: win32
Classifier: Intended Audience :: Science/Research
Classifier: Intended Audience :: Developers
Classifier: Intended Audience :: Education
Classifier: Programming Language :: Python :: 3
Classifier: Programming Language :: Python :: 3.10
Classifier: Programming Language :: Python :: 3.11
Classifier: Programming Language :: Python :: 3.12
Classifier: Programming Language :: Python :: 3.13
Classifier: Operating System :: POSIX :: Linux
Classifier: Operating System :: POSIX
Classifier: Operating System :: Unix
Classifier: Operating System :: MacOS
Classifier: Topic :: Scientific/Engineering
Classifier: Topic :: Scientific/Engineering :: Mathematics
Classifier: Topic :: Scientific/Engineering :: Physics
Classifier: Topic :: Scientific/Engineering :: Visualization
Classifier: Topic :: Software Development :: Libraries
Classifier: Topic :: Software Development :: Libraries :: Python Modules
Requires-Python: >=3.11
License-File: LICENSE
Requires-Dist: numpy>=2.3.0
Requires-Dist: matplotlib>=3.10.5
Requires-Dist: scipy>=1.16.0
Provides-Extra: test
Requires-Dist: pytest>=8.4.0; extra == "test"
Requires-Dist: pytest-cov>=4.1.0; extra == "test"
Requires-Dist: codecov>=2.1.13; extra == "test"
Requires-Dist: pytest-benchmark>=4.0.0; extra == "test"
Requires-Dist: pre-commit>=4.2.0; extra == "test"
Provides-Extra: dev
Requires-Dist: ruff>=0.12.8; extra == "dev"
Requires-Dist: mypy>=1.17.0; extra == "dev"
Requires-Dist: pre-commit>=4.2.0; extra == "dev"
Requires-Dist: pyright>=1.1.400; extra == "dev"
Requires-Dist: build>=1.0.3; extra == "dev"
Requires-Dist: twine>=4.0.2; extra == "dev"
Provides-Extra: all
Requires-Dist: interpolatepy[dev,test]; extra == "all"
Dynamic: license-file
